pyvttl/__init__.py
pyvttl/province.py
pyvttl/vttl_api.py
pyvttl/vttl_types.py
pyvttl-0.1.0.dist-info/licenses/LICENSE
pyvttl-0.1.0.dist-info/METADATA
pyvttl-0.1.0.dist-info/WHEEL
pyvttl-0.1.0.dist-info/top_level.txt
pyvttl-0.1.0.dist-info/RECORD
