Metadata-Version: 2.4
Name: pyvttl
Version: 0.1.0
Summary: Python wrapper for the VTTL SOAP API (read-only)
Home-page: https://github.com/jacobstim/pyvttl
Author: Tim Jacobs
Author-email: Tim Jacobs <jacobs.tim@gmail.com>
License: MIT License
Requires-Python: >=3.7
License-File: LICENSE
Requires-Dist: zeep
Dynamic: author
Dynamic: home-page
Dynamic: license-file
Dynamic: requires-python
